hack0/__init__.py
hack0/hack0.py
hack0-0.0.0.1.dist-info/LICENSE
hack0-0.0.0.1.dist-info/METADATA
hack0-0.0.0.1.dist-info/WHEEL
hack0-0.0.0.1.dist-info/top_level.txt
hack0-0.0.0.1.dist-info/RECORD
