Metadata-Version: 2.1
Name: hack0
Version: 0.0.0.1
Summary: Module under development.
Author: ZerProg studio
License-File: LICENSE
